<?xml version="1.0" encoding="UTF-8"?>
<configuration>
    <include resource="org/springframework/boot/logging/logback/defaults.xml"/>
    
    <!-- Console Appender with JSON formatting for production -->
    <appender name="JSON_CONSOLE" class="ch.qos.logback.core.ConsoleAppender">
        <encoder class="net.logstash.logback.encoder.LogstashEncoder">
            <!-- Include MDC (Mapped Diagnostic Context) fields -->
            <includeMdcKeyName>traceId</includeMdcKeyName>
            <includeMdcKeyName>spanId</includeMdcKeyName>
            <includeMdcKeyName>userId</includeMdcKeyName>
            <includeMdcKeyName>operation</includeMdcKeyName>
            <includeMdcKeyName>email</includeMdcKeyName>
            
            <!-- Custom fields -->
            <customFields>{"application":"employee-service","environment":"${ENVIRONMENT:-dev}"}</customFields>
            
            <!-- Timestamp format -->
            <timestampPattern>yyyy-MM-dd'T'HH:mm:ss.SSSZZ</timestampPattern>
        </encoder>
    </appender>
    
    <!-- Standard Console Appender for local development -->
    <appender name="CONSOLE" class="ch.qos.logback.core.ConsoleAppender">
        <encoder>
            <pattern>%d{yyyy-MM-dd HH:mm:ss.SSS} [%thread] %-5level %logger{36} - %msg%n</pattern>
        </encoder>
    </appender>
    
    <!-- File Appender for persistent logs -->
    <appender name="FILE" class="ch.qos.logback.core.rolling.RollingFileAppender">
        <file>/var/log/app/employee-service.log</file>
        <rollingPolicy class="ch.qos.logback.core.rolling.TimeBasedRollingPolicy">
            <fileNamePattern>/var/log/app/employee-service.%d{yyyy-MM-dd}.log</fileNamePattern>
            <maxHistory>30</maxHistory>
            <totalSizeCap>1GB</totalSizeCap>
        </rollingPolicy>
        <encoder class="net.logstash.logback.encoder.LogstashEncoder">
            <includeMdcKeyName>traceId</includeMdcKeyName>
            <includeMdcKeyName>spanId</includeMdcKeyName>
            <includeMdcKeyName>userId</includeMdcKeyName>
            <includeMdcKeyName>operation</includeMdcKeyName>
        </encoder>
    </appender>
    
    <!-- Async wrapper for better performance -->
    <appender name="ASYNC_JSON" class="ch.qos.logback.classic.AsyncAppender">
        <queueSize>512</queueSize>
        <discardingThreshold>0</discardingThreshold>
        <appender-ref ref="JSON_CONSOLE"/>
    </appender>
    
    <!-- Logger configurations -->
    <logger name="com.ibm.fscc.employeeservice" level="INFO"/>
    <logger name="org.springframework.kafka" level="WARN"/>
    <logger name="org.springframework.web" level="INFO"/>
    <logger name="org.hibernate.SQL" level="DEBUG"/>
    <logger name="org.hibernate.type.descriptor.sql.BasicBinder" level="TRACE"/>
    
    <!-- Profile-specific configurations -->
    <springProfile name="dev,local">
        <root level="INFO">
            <appender-ref ref="CONSOLE"/>
        </root>
    </springProfile>
    
    <springProfile name="prod,staging">
        <root level="INFO">
            <appender-ref ref="ASYNC_JSON"/>
            <appender-ref ref="FILE"/>
        </root>
    </springProfile>
    
    <!-- Default profile -->
    <springProfile name="default">
        <root level="INFO">
            <appender-ref ref="CONSOLE"/>
        </root>
    </springProfile>
</configuration>